{
  "go": {
    "FareDataId": 2,
    "Airline": "VJ",
    "AirlineObj": {
      "code": "VJ",
      "nameVi": "Vietjet Air",
      "nameEn": "Vietjet Air",
      "airLineGroup": "LCC",
      "logo": "https://static-image.adavigo.com/uploads/images/vj.gif"
    },
    "Itinerary": 1,
    "Leg": 0,
    "Promo": false,
    "Currency": "VND",
    "System": "VJ",
    "FareType": "agent",
    "CacheAge": 3,
    "Availability": 41,
    "Adt": 1,
    "Chd": 0,
    "Inf": 0,
    "FareAdt": 790000,
    "FareChd": 0,
    "FareInf": 0,
    "TaxAdt": 646600,
    "TaxChd": 0,
    "TaxInf": 0,
    "FeeAdt": 0,
    "FeeChd": 0,
    "FeeInf": 0,
    "ServiceFeeAdt": 0,
    "ServiceFeeChd": 0,
    "ServiceFeeInf": 0,
    "TotalNetPrice": 1436600,
    "TotalServiceFee": 0,
    "TotalDiscount": 0,
    "TotalCommission": 0,
    "TotalPrice": 1436600,
    "AdavigoPrice": {
      "price": 1491600,
      "amount": 1491600,
      "price_id": 2560,
      "profit": 55000
    },
    "AdavigoPriceAdt": {
      "price": 1491600,
      "amount": 1491600,
      "price_id": 2560,
      "profit": 55000
    },
    "ListFlight": [
      {
        "FlightId": 0,
        "Airline": "VJ",
        "Operating": "VJ",
        "Leg": 0,
        "StartPoint": "HAN",
        "EndPoint": "PQC",
        "StartDate": "2024-10-20T10:00:00",
        "EndDate": "2024-10-20T12:05:00",
        "StartDt": "20102024 10:00:00",
        "EndDt": "20102024 12:05:00",
        "FlightNumber": "VJ455",
        "StopNum": 0,
        "HasDownStop": false,
        "Duration": 125,
        "NoRefund": true,
        "GroupClass": "Economy",
        "GroupClassObj": {
          "id": 2750,
          "airline": "VJ",
          "classCode": "*_ECO",
          "fareType": "Economy",
          "detailVi": "ECO",
          "detailEn": "ECO",
          "description": "<li  style=\"padding-left: 0px !important;\"><img src=\"https://static-image.adavigo.com/uploads/images/webicons/ticket.svg\"><span style=\"margin-left: 10px;\">Thay đổi vé mất phí + chênh lệch nếu có</span></li><li  style=\"padding-left: 0px !important;\"><img src=\"https://static-image.adavigo.com/uploads/images/webicons/ticket.svg\"><span style=\"margin-left: 10px;\">Hoàn bảo lưu định danh tên khách trước 24h so với giờ khởi hành</span></li><li  style=\"padding-left: 0px !important;\"><img src=\"https://static-image.adavigo.com/uploads/images/webicons/ticket2.svg\"><span style=\"margin-left: 10px; \">Không đổi tên</span></li>"
        },
        "FareClass": "Z1_ECO",
        "FareBasis": "",
        "SeatRemain": 41,
        "Promo": false,
        "FlightValue": "0VJ455Z1_ECOHANPQC202410201000",
        "ListSegment": [
          {
            "Id": 0,
            "Airline": "VJ",
            "MarketingAirline": "VJ",
            "OperatingAirline": "VJ",
            "StartPoint": "HAN",
            "EndPoint": "PQC",
            "StartTime": "2024-10-20T10:00:00",
            "StartTimeZoneOffset": "+07:00",
            "EndTime": "2024-10-20T12:05:00",
            "EndTimeZoneOffset": "+07:00",
            "StartTm": "20102024 10:00:00",
            "EndTm": "20102024 12:05:00",
            "FlightNumber": "VJ455",
            "Duration": 125,
            "Class": "Z1_ECO",
            "Cabin": "Economy",
            "FareBasis": null,
            "Seat": 41,
            "Plane": "321",
            "StartTerminal": null,
            "EndTerminal": null,
            "HasStop": false,
            "StopPoint": null,
            "StopTime": 0,
            "DayChange": false,
            "StopOvernight": false,
            "ChangeStation": false,
            "ChangeAirport": false,
            "LastItem": true,
            "HandBaggage": "7kg",
            "AllowanceBaggage": ""
          }
        ]
      }
    ],
    "Profit": 110000,
    "Amount": 1546600
  },
  "extraInfo": {
    "DurationFlyGo": "2h5m",
    "FirstTimeGo": "\\n                                 10\\n                        :\\n                        00\\n                            ",
    "LastTimeGo": "\\n                                 12\\n                        :\\n                        05\\n                            ",
    "FirstDateGo": "\\n                               20/10/2024\\n                            ",
    "LastDateGo": "20/10/2024",
    "EndPointName": "Phú Quốc",
    "StartPointName": "Hà Nội",
    "StringDateGoChoosen": "Chủ nhật, 20 tháng 10",
    "StringDateBackChoosen": "Thứ 3, 22 tháng 10",
    "DurationFlyBack": "2h5m",
    "FirstTimeBack": "\\n                                 14\\n                        :\\n                        15\\n                            ",
    "LastTimeBack": "\\n                                 16\\n                        :\\n                        20\\n                            ",
    "FirstDateBack": "\\n                               20/10/2024\\n                            ",
    "LastDateBack": "20/10/2024"
  },
  "search": {
    "StartPoint": "HAN",
    "EndPoint": "PQC",
    "StartDate": "21/10/2024",
    "EndDate": "23/10/2024",
    "Adt": 2,
    "Child": 0,
    "Baby": 0
  },
  "back": {
    "FareDataId": 1,
    "Airline": "VJ",
    "AirlineObj": {
      "code": "VJ",
      "nameVi": "Vietjet Air",
      "nameEn": "Vietjet Air",
      "airLineGroup": "LCC",
      "logo": "https://static-image.adavigo.com/uploads/images/vj.gif"
    },
    "Itinerary": 1,
    "Leg": 0,
    "Promo": false,
    "Currency": "VND",
    "System": "VJ",
    "FareType": "agent",
    "CacheAge": 5,
    "Availability": 25,
    "Adt": 2,
    "Chd": 0,
    "Inf": 0,
    "FareAdt": 590000,
    "FareChd": 0,
    "FareInf": 0,
    "TaxAdt": 630600,
    "TaxChd": 0,
    "TaxInf": 0,
    "FeeAdt": 0,
    "FeeChd": 0,
    "FeeInf": 0,
    "ServiceFeeAdt": 0,
    "ServiceFeeChd": 0,
    "ServiceFeeInf": 0,
    "TotalNetPrice": 2441200,
    "TotalServiceFee": 0,
    "TotalDiscount": 0,
    "TotalCommission": 0,
    "TotalPrice": 2441200,
    "AdavigoPrice": {
      "price": 2496200,
      "amount": 2496200,
      "price_id": 2560,
      "profit": 55000
    },
    "AdavigoPriceAdt": {
      "price": 1275600,
      "amount": 1275600,
      "price_id": 2560,
      "profit": 55000
    },
    "ListFlight": [
      {
        "FlightId": 0,
        "Airline": "VJ",
        "Operating": "VJ",
        "Leg": 0,
        "StartPoint": "HAN",
        "EndPoint": "PQC",
        "StartDate": "2024-10-20T14:15:00",
        "EndDate": "2024-10-20T16:20:00",
        "StartDt": "20102024 14:15:00",
        "EndDt": "20102024 16:20:00",
        "FlightNumber": "VJ459",
        "StopNum": 0,
        "HasDownStop": false,
        "Duration": 125,
        "NoRefund": true,
        "GroupClass": "Economy",
        "GroupClassObj": {
          "id": 2750,
          "airline": "VJ",
          "classCode": "*_ECO",
          "fareType": "Economy",
          "detailVi": "ECO",
          "detailEn": "ECO",
          "description": "<li  style=\"padding-left: 0px !important;\"><img src=\"https://static-image.adavigo.com/uploads/images/webicons/ticket.svg\"><span style=\"margin-left: 10px;\">Thay đổi vé mất phí + chênh lệch nếu có</span></li><li  style=\"padding-left: 0px !important;\"><img src=\"https://static-image.adavigo.com/uploads/images/webicons/ticket.svg\"><span style=\"margin-left: 10px;\">Hoàn bảo lưu định danh tên khách trước 24h so với giờ khởi hành</span></li><li  style=\"padding-left: 0px !important;\"><img src=\"https://static-image.adavigo.com/uploads/images/webicons/ticket2.svg\"><span style=\"margin-left: 10px; \">Không đổi tên</span></li>"
        },
        "FareClass": "A1_ECO",
        "FareBasis": "",
        "SeatRemain": 25,
        "Promo": false,
        "FlightValue": "0VJ459A1_ECOHANPQC202410201415",
        "ListSegment": [
          {
            "Id": 0,
            "Airline": "VJ",
            "MarketingAirline": "VJ",
            "OperatingAirline": "VJ",
            "StartPoint": "HAN",
            "EndPoint": "PQC",
            "StartTime": "2024-10-20T14:15:00",
            "StartTimeZoneOffset": "+07:00",
            "EndTime": "2024-10-20T16:20:00",
            "EndTimeZoneOffset": "+07:00",
            "StartTm": "20102024 14:15:00",
            "EndTm": "20102024 16:20:00",
            "FlightNumber": "VJ459",
            "Duration": 125,
            "Class": "A1_ECO",
            "Cabin": "Economy",
            "FareBasis": null,
            "Seat": 25,
            "Plane": "321",
            "StartTerminal": null,
            "EndTerminal": null,
            "HasStop": false,
            "StopPoint": null,
            "StopTime": 0,
            "DayChange": false,
            "StopOvernight": false,
            "ChangeStation": false,
            "ChangeAirport": false,
            "LastItem": true,
            "HandBaggage": "7kg",
            "AllowanceBaggage": ""
          }
        ]
      }
    ],
    "Profit": 110000,
    "Amount": 2551200
  },
  "Session": "DC12508HANPQC201024PQCHAN221024200113720",
  "isTwoWayFare": true,
  "filterFare": {
    "takeOffTime": [],
    "airlineCompany": [],
    "ticketClass": [],
    "stopNum": [],
    "minValue": 0,
    "maxValue": 13060000
  }
}
